paystack_cli/__init__.py
paystack_cli/__main__.py
paystack_cli/apple_pay.py
paystack_cli/bulk_charges.py
paystack_cli/charge.py
paystack_cli/customers.py
paystack_cli/dedicated_virtual_accounts.py
paystack_cli/disputes.py
paystack_cli/integration.py
paystack_cli/miscellaneous.py
paystack_cli/payment_pages.py
paystack_cli/payments_requests.py
paystack_cli/plans.py
paystack_cli/products.py
paystack_cli/refunds.py
paystack_cli/settlements.py
paystack_cli/subaccounts.py
paystack_cli/subscriptions.py
paystack_cli/terminals.py
paystack_cli/transactions.py
paystack_cli/transactions_splits.py
paystack_cli/transfer_recipients.py
paystack_cli/transfers.py
paystack_cli/transfers_control.py
paystack_cli/utils.py
paystack_cli/verification.py
paystack_cli-0.2.1.dist-info/METADATA
paystack_cli-0.2.1.dist-info/WHEEL
paystack_cli-0.2.1.dist-info/entry_points.txt
paystack_cli-0.2.1.dist-info/licenses/LICENSE
paystack_cli-0.2.1.dist-info/RECORD
