Metadata-Version: 2.3
Name: paystack-cli
Version: 0.2.1
Summary: A command line app for interacting with Paystack's API
Author-email: Gbenga Adeyi <adeyigbenga005@gmail.com>
License: MIT
Keywords: paystack,paystack-python,paystackapi,pypaystack
Classifier: License :: OSI Approved :: MIT License
Classifier: Programming Language :: Python
Classifier: Programming Language :: Python :: 3
Requires-Python: >=3.11
Requires-Dist: pypaystack2>=2.1.1
Requires-Dist: typer-slim[standard]>=0.15.1
